openinference/instrumentation/agentspec/__init__.py
openinference/instrumentation/agentspec/_openinference_spanprocessor.py
openinference/instrumentation/agentspec/_opentelemetry_spanprocessor.py
openinference/instrumentation/agentspec/py.typed
openinference/instrumentation/agentspec/version.py
openinference_instrumentation_agentspec-0.1.0.dist-info/METADATA
openinference_instrumentation_agentspec-0.1.0.dist-info/WHEEL
openinference_instrumentation_agentspec-0.1.0.dist-info/entry_points.txt
openinference_instrumentation_agentspec-0.1.0.dist-info/licenses/LICENSE
openinference_instrumentation_agentspec-0.1.0.dist-info/RECORD
